rrpmpkg/__init__.py
rrpmpkg/__main__.py
rrpmpkg/rrpmpkg.py
rrpmpkg-1.0.2.dist-info/LICENSE
rrpmpkg-1.0.2.dist-info/WHEEL
rrpmpkg-1.0.2.dist-info/METADATA
rrpmpkg-1.0.2.dist-info/RECORD
