Metadata-Version: 2.1
Name: rrpmpkg
Version: 1.0.2
Summary: RRPM's Package Manager
Author: pybash1
Author-email: 67195650+pybash1@users.noreply.github.com
Requires-Python: >=3.7,<4.0
Classifier: Programming Language :: Python :: 3
Classifier: Programming Language :: Python :: 3.10
Classifier: Programming Language :: Python :: 3.7
Classifier: Programming Language :: Python :: 3.8
Classifier: Programming Language :: Python :: 3.9
Requires-Dist: requests (>=2.28.0,<3.0.0)
Requires-Dist: rich (>=12.4.4,<13.0.0)
Requires-Dist: typer (>=0.4.1,<0.5.0)
